erc20_scanner/__init__.py
erc20_scanner-1.0.0.dist-info/METADATA
erc20_scanner-1.0.0.dist-info/WHEEL
erc20_scanner-1.0.0.dist-info/top_level.txt
erc20_scanner-1.0.0.dist-info/RECORD
