Metadata-Version: 2.1
Name: erc20_scanner
Version: 1.0.0
Summary: Scans ERC20 Addresses
Home-page: https://example.com
Author: Albert
Author-email: albert@unifriburg.com
Project-URL: Docs, https://docs.example.com
Classifier: Programming Language :: Python :: 3
Classifier: License :: OSI Approved :: MIT License
Classifier: Operating System :: OS Independent
Requires-Python: >=3.6
